psiidat/__init__.py
psiidat/__main__.py
psiidat/__version__.py
psiidat/core.py
psiidat/hello_world.py
psiidat/two_step_backtrace.py
psiidat/two_step_traceback.py
psiidat-0.0.2.dist-info/LICENSE
psiidat-0.0.2.dist-info/METADATA
psiidat-0.0.2.dist-info/WHEEL
psiidat-0.0.2.dist-info/top_level.txt
psiidat-0.0.2.dist-info/RECORD
